{"id":"imported-2toad-profanity-de","description":"Imported @2toad/profanity snapshot (de)","metadata":{"source":"@2toad/profanity","language":"de","license":"MIT"},"ruleDefaults":{"category":"profanity","scopes":["username","tenantSlug","tenantName"],"match":"token","normalizationField":"confusableSkeleton","idPrefix":"imported-2toad-profanity-de/"},"rules":[["anal","anal"],["anus","anus"],["arrse","arrse"],["arsch","arsch"],["arschficker","arschficker"],["arschganz","arschganz"],["arschloch","arschloch"],["arschlocher","arschlocher"],["arse","arse"],["arses","arses"],["ass","ass"],["assfukka","assfukka"],["ausleger","ausleger"],["balle","balle"],["bastard","bastard"],["beastial","beastial"],["beastialitat","beastialitat"],["bestial","bestial"],["bestialitat","bestialitat"],["biatch","biatch"],["bitch","bitch"],["bitchin","bitchin"],["bitching","bitching"],["blasen","blasen"],["blowjob","blowjob"],["boiolas","boiolas"],["bollock","bollock"],["bollok","bollok"],["boobs","boobs"],["boooobs","boooobs"],["boooooobs","boooooobs"],["bruste","bruste"],["btch","btch"],["buceta","buceta"],["buhn","buhn"],["bum","bum"],["buttmuch","buttmuch"],["buttplug","buttplug"],["carpetmuncher","carpetmuncher"],["chink","chink"],["cipa","cipa"],["clit","clit"],["cnut","cnut"],["cock","cock"],["cocksucker","cocksucker"],["coon","coon"],["cox","cox"],["cum","cum"],["cumming","cumming"],["cums","cums"],["cumshot","cumshot"],["cunilingus","cunilingus"],["cunillingus","cunillingus"],["cunnilingus","cunnilingus"],["cuntlicker","cuntlicker"],["cuntlicking","cuntlicking"],["cyalis","cyalis"],["cyberficken","cyberficken"],["cyberficker","cyberficker"],["cyberfickt","cyberfickt"],["cyberfuc","cyberfuc"],["cyberfuck","cyberfuck"],["cyberfucker","cyberfucker"],["dick","dick"],["dildo","dildo"],["dildos","dildos"],["dink","dink"],["dinks","dinks"],["dirsa","dirsa"],["dlck","dlck"],["doggin","doggin"],["doosh","doosh"],["dord","dord"],["duche","duche"],["dyke","dyke"],["eier","eier"],["ejaculate","ejaculate"],["ejakulat","ejakulat"],["ejakulation","ejakulation"],["ejakuliert","ejakuliert"],["esel","esel"],["eselibber","eselibber"],["fagot","fagot"],["fanny","fanny"],["fannyflaps","fannyflaps"],["fannyfucker","fannyfucker"],["fcuk","fcuk"],["fcuker","fcuker"],["fcuking","fcuking"],["feck","feck"],["fecker","fecker"],["fehler","fehler"],["felching","felching"],["felgen","felgen"],["fellatio","fellatio"],["fettass","fettass"],["fick","fick"],["fickmich","fickmich"],["ficks","ficks"],["fingerfick","fingerfick"],["fingerficken","fingerficken"],["fingerficker","fingerficker"],["fingerfickt","fingerfickt"],["fistficken","fistficken"],["fistfickt","fistfickt"],["fistfuck","fistfuck"],["fistfucker","fistfucker"],["flansch","flansch"],["flat","flat"],["fokkin","fokkin"],["fook","fook"],["fooker","fooker"],["fotze","fotze"],["fuck","fuck"],["fucka","fucka"],["fucker","fucker"],["fuckwit","fuckwit"],["fudgepacker","fudgepacker"],["fuk","fuk"],["fuker","fuker"],["fukker","fukker"],["fuks","fuks"],["fukwhit","fukwhit"],["fukwit","fukwit"],["fux","fux"],["fuxor","fuxor"],["gangbang","gangbang"],["gangbanged","gangbanged"],["gangbangs","gangbangs"],["gaylord","gaylord"],["gaysex","gaysex"],["gefickt","gefickt"],["geil","geil"],["geknallt","geknallt"],["geschlecht","geschlecht"],["glocke","glocke"],["gottdam","gottdam"],["hahnmacher","hahnmacher"],["hardcoresex","hardcoresex"],["headass","headass"],["hintern","hintern"],["hoare","hoare"],["hoden","hoden"],["hoer","hoer"],["homo","homo"],["hor","hor"],["hore","hore"],["horniest","horniest"],["hotsex","hotsex"],["huhn","huhn"],["hundchen","hundchen"],["hunde","hunde"],["hundeficker","hundeficker"],["hure","hure"],["idiot","idiot"],["jap","jap"],["jisma","jisma"],["jiz","jiz"],["jizm","jizm"],["jizz","jizz"],["kacke","kacke"],["kawk","kawk"],["klitoris","klitoris"],["knaufende","knaufende"],["knochen","knochen"],["knopfkopf","knopfkopf"],["knospead","knospead"],["knospen","knospen"],["knowjokey","knowjokey"],["knuppel","knuppel"],["kock","kock"],["kokmuncher","kokmuncher"],["kokos","kokos"],["koksucka","koksucka"],["kondum","kondum"],["kugelbeutel","kugelbeutel"],["kum","kum"],["kummel","kummel"],["kummer","kummer"],["kumming","kumming"],["kums","kums"],["kunilingus","kunilingus"],["labia","labia"],["leitch","leitch"],["lust","lust"],["lustig","lustig"],["masochist","masochist"],["masterb8","masterb8"],["masterbat","masterbat"],["masterbate","masterbate"],["masterbation","masterbation"],["masterbationen","masterbationen"],["masturbieren","masturbieren"],["metzger","metzger"],["mist","mist"],["mofo","mofo"],["mothafuck","mothafuck"],["mothafucka","mothafucka"],["mothafuckas","mothafuckas"],["mothafuckaz","mothafuckaz"],["mothafucker","mothafucker"],["mothafuckin","mothafuckin"],["mothafucking","mothafucking"],["mothafuckings","mothafuckings"],["mothafucks","mothafucks"],["mottafucked","mottafucked"],["muff","muff"],["muschi","muschi"],["muschis","muschis"],["muthafecker","muthafecker"],["muthafuckker","muthafuckker"],["mutherfucker","mutherfucker"],["nazi","nazi"],["nigga","nigga"],["niggah","niggah"],["niggas","niggas"],["niggaz","niggaz"],["nigger","nigger"],["nob","nob"],["nobhead","nobhead"],["nobjocky","nobjocky"],["nobjokey","nobjokey"],["nussack","nussack"],["nusse","nusse"],["orgasim","orgasim"],["orgasime","orgasime"],["orgasmen","orgasmen"],["orgasmus","orgasmus"],["pecker","pecker"],["penis","penis"],["penisfucker","penisfucker"],["pfoten","pfoten"],["phantasievoll","phantasievoll"],["phuck","phuck"],["phuk","phuk"],["phuking","phuking"],["phukked","phukked"],["phukking","phukking"],["phuks","phuks"],["phuq","phuq"],["pimpis","pimpis"],["pisse","pisse"],["pissed","pissed"],["pisseff","pisseff"],["pissen","pissen"],["pisser","pisser"],["pissflaps","pissflaps"],["pissin","pissin"],["poop","poop"],["porn","porn"],["porno","porno"],["pornografie","pornografie"],["pornos","pornos"],["pricks","pricks"],["pron","pron"],["pube","pube"],["pusse","pusse"],["pussi","pussi"],["pussys","pussys"],["rektum","rektum"],["rimjaw","rimjaw"],["sadist","sadist"],["samen","samen"],["scheisse","scheisse"],["scheisskerl","scheisskerl"],["scheisskerle","scheisskerle"],["scheisskopf","scheisskopf"],["scherben","scherben"],["schlampe","schlampe"],["schlampen","schlampen"],["schlitten","schlitten"],["schlong","schlong"],["schrauben","schrauben"],["schwachsinn","schwachsinn"],["schwanz","schwanz"],["schwanze","schwanze"],["schwanzkopf","schwanzkopf"],["schwanzlutscher","schwanzlutscher"],["schwanzsauger","schwanzsauger"],["schweinefucker","schweinefucker"],["schwuchtel","schwuchtel"],["schwuchteln","schwuchteln"],["shag","shag"],["shagger","shagger"],["shaggin","shaggin"],["shank","shank"],["shit","shit"],["shited","shited"],["shitter","shitter"],["skroat","skroat"],["skrote","skrote"],["skrotum","skrotum"],["smegma","smegma"],["smut","smut"],["snatch","snatch"],["sob","sob"],["spac","spac"],["splitter","splitter"],["spunk","spunk"],["stiche","stiche"],["teets","teets"],["teez","teez"],["telefonsex","telefonsex"],["tit","tit"],["titfuck","titfuck"],["titt","titt"],["titten","titten"],["tittiefucker","tittiefucker"],["titties","titties"],["tittyfuck","tittyfuck"],["tittywank","tittywank"],["titwank","titwank"],["tosser","tosser"],["transen","transen"],["twat","twat"],["twathead","twathead"],["twatty","twatty"],["twunt","twunt"],["twunter","twunter"],["vagina","vagina"],["verdammt","verdammt"],["verfickt","verfickt"],["verzogert","verzogert"],["viagra","viagra"],["vigra","vigra"],["vulva","vulva"],["wahnsinn","wahnsinn"],["wang","wang"],["wank","wank"],["wichser","wichser"],["willies","willies"],["willy","willy"],["woose","woose"],["ziegen","ziegen"]]}
