{
  "id": "imported-ldnoobw-de",
  "description": "Imported LDNOOBW snapshot (de)",
  "metadata": {
    "source": "LDNOOBW",
    "language": "de",
    "severity": "mixed",
    "tags": [
      "external-import",
      "profanity"
    ],
    "sourceUrl": "https://raw.githubusercontent.com/LDNOOBW/List-of-Dirty-Naughty-Obscene-and-Otherwise-Bad-Words/master/de"
  },
  "rules": [
    {
      "id": "imported-ldnoobw-de/analritter",
      "term": "analritter",
      "category": "profanity",
      "scopes": [
        "username",
        "tenantSlug",
        "tenantName"
      ],
      "match": "token",
      "normalizationField": "confusableSkeleton",
      "metadata": {
        "source": "LDNOOBW",
        "language": "de",
        "severity": "mixed",
        "tags": [
          "external-import",
          "profanity"
        ],
        "sourceUrl": "https://raw.githubusercontent.com/LDNOOBW/List-of-Dirty-Naughty-Obscene-and-Otherwise-Bad-Words/master/de"
      }
    },
    {
      "id": "imported-ldnoobw-de/arsch",
      "term": "arsch",
      "category": "profanity",
      "scopes": [
        "username",
        "tenantSlug",
        "tenantName"
      ],
      "match": "token",
      "normalizationField": "confusableSkeleton",
      "metadata": {
        "source": "LDNOOBW",
        "language": "de",
        "severity": "mixed",
        "tags": [
          "external-import",
          "profanity"
        ],
        "sourceUrl": "https://raw.githubusercontent.com/LDNOOBW/List-of-Dirty-Naughty-Obscene-and-Otherwise-Bad-Words/master/de"
      }
    },
    {
      "id": "imported-ldnoobw-de/arschficker",
      "term": "arschficker",
      "category": "profanity",
      "scopes": [
        "username",
        "tenantSlug",
        "tenantName"
      ],
      "match": "token",
      "normalizationField": "confusableSkeleton",
      "metadata": {
        "source": "LDNOOBW",
        "language": "de",
        "severity": "mixed",
        "tags": [
          "external-import",
          "profanity"
        ],
        "sourceUrl": "https://raw.githubusercontent.com/LDNOOBW/List-of-Dirty-Naughty-Obscene-and-Otherwise-Bad-Words/master/de"
      }
    },
    {
      "id": "imported-ldnoobw-de/arschlecker",
      "term": "arschlecker",
      "category": "profanity",
      "scopes": [
        "username",
        "tenantSlug",
        "tenantName"
      ],
      "match": "token",
      "normalizationField": "confusableSkeleton",
      "metadata": {
        "source": "LDNOOBW",
        "language": "de",
        "severity": "mixed",
        "tags": [
          "external-import",
          "profanity"
        ],
        "sourceUrl": "https://raw.githubusercontent.com/LDNOOBW/List-of-Dirty-Naughty-Obscene-and-Otherwise-Bad-Words/master/de"
      }
    },
    {
      "id": "imported-ldnoobw-de/arschloch",
      "term": "arschloch",
      "category": "profanity",
      "scopes": [
        "username",
        "tenantSlug",
        "tenantName"
      ],
      "match": "token",
      "normalizationField": "confusableSkeleton",
      "metadata": {
        "source": "LDNOOBW",
        "language": "de",
        "severity": "mixed",
        "tags": [
          "external-import",
          "profanity"
        ],
        "sourceUrl": "https://raw.githubusercontent.com/LDNOOBW/List-of-Dirty-Naughty-Obscene-and-Otherwise-Bad-Words/master/de"
      }
    },
    {
      "id": "imported-ldnoobw-de/bimbo",
      "term": "bimbo",
      "category": "profanity",
      "scopes": [
        "username",
        "tenantSlug",
        "tenantName"
      ],
      "match": "token",
      "normalizationField": "confusableSkeleton",
      "metadata": {
        "source": "LDNOOBW",
        "language": "de",
        "severity": "mixed",
        "tags": [
          "external-import",
          "profanity"
        ],
        "sourceUrl": "https://raw.githubusercontent.com/LDNOOBW/List-of-Dirty-Naughty-Obscene-and-Otherwise-Bad-Words/master/de"
      }
    },
    {
      "id": "imported-ldnoobw-de/bonze",
      "term": "bonze",
      "category": "profanity",
      "scopes": [
        "username",
        "tenantSlug",
        "tenantName"
      ],
      "match": "token",
      "normalizationField": "confusableSkeleton",
      "metadata": {
        "source": "LDNOOBW",
        "language": "de",
        "severity": "mixed",
        "tags": [
          "external-import",
          "profanity"
        ],
        "sourceUrl": "https://raw.githubusercontent.com/LDNOOBW/List-of-Dirty-Naughty-Obscene-and-Otherwise-Bad-Words/master/de"
      }
    },
    {
      "id": "imported-ldnoobw-de/bratze",
      "term": "bratze",
      "category": "profanity",
      "scopes": [
        "username",
        "tenantSlug",
        "tenantName"
      ],
      "match": "token",
      "normalizationField": "confusableSkeleton",
      "metadata": {
        "source": "LDNOOBW",
        "language": "de",
        "severity": "mixed",
        "tags": [
          "external-import",
          "profanity"
        ],
        "sourceUrl": "https://raw.githubusercontent.com/LDNOOBW/List-of-Dirty-Naughty-Obscene-and-Otherwise-Bad-Words/master/de"
      }
    },
    {
      "id": "imported-ldnoobw-de/bumsen",
      "term": "bumsen",
      "category": "profanity",
      "scopes": [
        "username",
        "tenantSlug",
        "tenantName"
      ],
      "match": "token",
      "normalizationField": "confusableSkeleton",
      "metadata": {
        "source": "LDNOOBW",
        "language": "de",
        "severity": "mixed",
        "tags": [
          "external-import",
          "profanity"
        ],
        "sourceUrl": "https://raw.githubusercontent.com/LDNOOBW/List-of-Dirty-Naughty-Obscene-and-Otherwise-Bad-Words/master/de"
      }
    },
    {
      "id": "imported-ldnoobw-de/dödel",
      "term": "dödel",
      "category": "profanity",
      "scopes": [
        "username",
        "tenantSlug",
        "tenantName"
      ],
      "match": "token",
      "normalizationField": "confusableSkeleton",
      "metadata": {
        "source": "LDNOOBW",
        "language": "de",
        "severity": "mixed",
        "tags": [
          "external-import",
          "profanity"
        ],
        "sourceUrl": "https://raw.githubusercontent.com/LDNOOBW/List-of-Dirty-Naughty-Obscene-and-Otherwise-Bad-Words/master/de"
      }
    },
    {
      "id": "imported-ldnoobw-de/fick",
      "term": "fick",
      "category": "profanity",
      "scopes": [
        "username",
        "tenantSlug",
        "tenantName"
      ],
      "match": "token",
      "normalizationField": "confusableSkeleton",
      "metadata": {
        "source": "LDNOOBW",
        "language": "de",
        "severity": "mixed",
        "tags": [
          "external-import",
          "profanity"
        ],
        "sourceUrl": "https://raw.githubusercontent.com/LDNOOBW/List-of-Dirty-Naughty-Obscene-and-Otherwise-Bad-Words/master/de"
      }
    },
    {
      "id": "imported-ldnoobw-de/ficken",
      "term": "ficken",
      "category": "profanity",
      "scopes": [
        "username",
        "tenantSlug",
        "tenantName"
      ],
      "match": "token",
      "normalizationField": "confusableSkeleton",
      "metadata": {
        "source": "LDNOOBW",
        "language": "de",
        "severity": "mixed",
        "tags": [
          "external-import",
          "profanity"
        ],
        "sourceUrl": "https://raw.githubusercontent.com/LDNOOBW/List-of-Dirty-Naughty-Obscene-and-Otherwise-Bad-Words/master/de"
      }
    },
    {
      "id": "imported-ldnoobw-de/flittchen",
      "term": "flittchen",
      "category": "profanity",
      "scopes": [
        "username",
        "tenantSlug",
        "tenantName"
      ],
      "match": "token",
      "normalizationField": "confusableSkeleton",
      "metadata": {
        "source": "LDNOOBW",
        "language": "de",
        "severity": "mixed",
        "tags": [
          "external-import",
          "profanity"
        ],
        "sourceUrl": "https://raw.githubusercontent.com/LDNOOBW/List-of-Dirty-Naughty-Obscene-and-Otherwise-Bad-Words/master/de"
      }
    },
    {
      "id": "imported-ldnoobw-de/fotze",
      "term": "fotze",
      "category": "profanity",
      "scopes": [
        "username",
        "tenantSlug",
        "tenantName"
      ],
      "match": "token",
      "normalizationField": "confusableSkeleton",
      "metadata": {
        "source": "LDNOOBW",
        "language": "de",
        "severity": "mixed",
        "tags": [
          "external-import",
          "profanity"
        ],
        "sourceUrl": "https://raw.githubusercontent.com/LDNOOBW/List-of-Dirty-Naughty-Obscene-and-Otherwise-Bad-Words/master/de"
      }
    },
    {
      "id": "imported-ldnoobw-de/fratze",
      "term": "fratze",
      "category": "profanity",
      "scopes": [
        "username",
        "tenantSlug",
        "tenantName"
      ],
      "match": "token",
      "normalizationField": "confusableSkeleton",
      "metadata": {
        "source": "LDNOOBW",
        "language": "de",
        "severity": "mixed",
        "tags": [
          "external-import",
          "profanity"
        ],
        "sourceUrl": "https://raw.githubusercontent.com/LDNOOBW/List-of-Dirty-Naughty-Obscene-and-Otherwise-Bad-Words/master/de"
      }
    },
    {
      "id": "imported-ldnoobw-de/hackfresse",
      "term": "hackfresse",
      "category": "profanity",
      "scopes": [
        "username",
        "tenantSlug",
        "tenantName"
      ],
      "match": "token",
      "normalizationField": "confusableSkeleton",
      "metadata": {
        "source": "LDNOOBW",
        "language": "de",
        "severity": "mixed",
        "tags": [
          "external-import",
          "profanity"
        ],
        "sourceUrl": "https://raw.githubusercontent.com/LDNOOBW/List-of-Dirty-Naughty-Obscene-and-Otherwise-Bad-Words/master/de"
      }
    },
    {
      "id": "imported-ldnoobw-de/hure",
      "term": "hure",
      "category": "profanity",
      "scopes": [
        "username",
        "tenantSlug",
        "tenantName"
      ],
      "match": "token",
      "normalizationField": "confusableSkeleton",
      "metadata": {
        "source": "LDNOOBW",
        "language": "de",
        "severity": "mixed",
        "tags": [
          "external-import",
          "profanity"
        ],
        "sourceUrl": "https://raw.githubusercontent.com/LDNOOBW/List-of-Dirty-Naughty-Obscene-and-Otherwise-Bad-Words/master/de"
      }
    },
    {
      "id": "imported-ldnoobw-de/hurensohn",
      "term": "hurensohn",
      "category": "profanity",
      "scopes": [
        "username",
        "tenantSlug",
        "tenantName"
      ],
      "match": "token",
      "normalizationField": "confusableSkeleton",
      "metadata": {
        "source": "LDNOOBW",
        "language": "de",
        "severity": "mixed",
        "tags": [
          "external-import",
          "profanity"
        ],
        "sourceUrl": "https://raw.githubusercontent.com/LDNOOBW/List-of-Dirty-Naughty-Obscene-and-Otherwise-Bad-Words/master/de"
      }
    },
    {
      "id": "imported-ldnoobw-de/ische",
      "term": "ische",
      "category": "profanity",
      "scopes": [
        "username",
        "tenantSlug",
        "tenantName"
      ],
      "match": "token",
      "normalizationField": "confusableSkeleton",
      "metadata": {
        "source": "LDNOOBW",
        "language": "de",
        "severity": "mixed",
        "tags": [
          "external-import",
          "profanity"
        ],
        "sourceUrl": "https://raw.githubusercontent.com/LDNOOBW/List-of-Dirty-Naughty-Obscene-and-Otherwise-Bad-Words/master/de"
      }
    },
    {
      "id": "imported-ldnoobw-de/kackbratze",
      "term": "kackbratze",
      "category": "profanity",
      "scopes": [
        "username",
        "tenantSlug",
        "tenantName"
      ],
      "match": "token",
      "normalizationField": "confusableSkeleton",
      "metadata": {
        "source": "LDNOOBW",
        "language": "de",
        "severity": "mixed",
        "tags": [
          "external-import",
          "profanity"
        ],
        "sourceUrl": "https://raw.githubusercontent.com/LDNOOBW/List-of-Dirty-Naughty-Obscene-and-Otherwise-Bad-Words/master/de"
      }
    },
    {
      "id": "imported-ldnoobw-de/kacke",
      "term": "kacke",
      "category": "profanity",
      "scopes": [
        "username",
        "tenantSlug",
        "tenantName"
      ],
      "match": "token",
      "normalizationField": "confusableSkeleton",
      "metadata": {
        "source": "LDNOOBW",
        "language": "de",
        "severity": "mixed",
        "tags": [
          "external-import",
          "profanity"
        ],
        "sourceUrl": "https://raw.githubusercontent.com/LDNOOBW/List-of-Dirty-Naughty-Obscene-and-Otherwise-Bad-Words/master/de"
      }
    },
    {
      "id": "imported-ldnoobw-de/kacken",
      "term": "kacken",
      "category": "profanity",
      "scopes": [
        "username",
        "tenantSlug",
        "tenantName"
      ],
      "match": "token",
      "normalizationField": "confusableSkeleton",
      "metadata": {
        "source": "LDNOOBW",
        "language": "de",
        "severity": "mixed",
        "tags": [
          "external-import",
          "profanity"
        ],
        "sourceUrl": "https://raw.githubusercontent.com/LDNOOBW/List-of-Dirty-Naughty-Obscene-and-Otherwise-Bad-Words/master/de"
      }
    },
    {
      "id": "imported-ldnoobw-de/kackwurst",
      "term": "kackwurst",
      "category": "profanity",
      "scopes": [
        "username",
        "tenantSlug",
        "tenantName"
      ],
      "match": "token",
      "normalizationField": "confusableSkeleton",
      "metadata": {
        "source": "LDNOOBW",
        "language": "de",
        "severity": "mixed",
        "tags": [
          "external-import",
          "profanity"
        ],
        "sourceUrl": "https://raw.githubusercontent.com/LDNOOBW/List-of-Dirty-Naughty-Obscene-and-Otherwise-Bad-Words/master/de"
      }
    },
    {
      "id": "imported-ldnoobw-de/kampflesbe",
      "term": "kampflesbe",
      "category": "profanity",
      "scopes": [
        "username",
        "tenantSlug",
        "tenantName"
      ],
      "match": "token",
      "normalizationField": "confusableSkeleton",
      "metadata": {
        "source": "LDNOOBW",
        "language": "de",
        "severity": "mixed",
        "tags": [
          "external-import",
          "profanity"
        ],
        "sourceUrl": "https://raw.githubusercontent.com/LDNOOBW/List-of-Dirty-Naughty-Obscene-and-Otherwise-Bad-Words/master/de"
      }
    },
    {
      "id": "imported-ldnoobw-de/kanake",
      "term": "kanake",
      "category": "profanity",
      "scopes": [
        "username",
        "tenantSlug",
        "tenantName"
      ],
      "match": "token",
      "normalizationField": "confusableSkeleton",
      "metadata": {
        "source": "LDNOOBW",
        "language": "de",
        "severity": "mixed",
        "tags": [
          "external-import",
          "profanity"
        ],
        "sourceUrl": "https://raw.githubusercontent.com/LDNOOBW/List-of-Dirty-Naughty-Obscene-and-Otherwise-Bad-Words/master/de"
      }
    },
    {
      "id": "imported-ldnoobw-de/kimme",
      "term": "kimme",
      "category": "profanity",
      "scopes": [
        "username",
        "tenantSlug",
        "tenantName"
      ],
      "match": "token",
      "normalizationField": "confusableSkeleton",
      "metadata": {
        "source": "LDNOOBW",
        "language": "de",
        "severity": "mixed",
        "tags": [
          "external-import",
          "profanity"
        ],
        "sourceUrl": "https://raw.githubusercontent.com/LDNOOBW/List-of-Dirty-Naughty-Obscene-and-Otherwise-Bad-Words/master/de"
      }
    },
    {
      "id": "imported-ldnoobw-de/lümmel",
      "term": "lümmel",
      "category": "profanity",
      "scopes": [
        "username",
        "tenantSlug",
        "tenantName"
      ],
      "match": "token",
      "normalizationField": "confusableSkeleton",
      "metadata": {
        "source": "LDNOOBW",
        "language": "de",
        "severity": "mixed",
        "tags": [
          "external-import",
          "profanity"
        ],
        "sourceUrl": "https://raw.githubusercontent.com/LDNOOBW/List-of-Dirty-Naughty-Obscene-and-Otherwise-Bad-Words/master/de"
      }
    },
    {
      "id": "imported-ldnoobw-de/milf",
      "term": "milf",
      "category": "profanity",
      "scopes": [
        "username",
        "tenantSlug",
        "tenantName"
      ],
      "match": "token",
      "normalizationField": "confusableSkeleton",
      "metadata": {
        "source": "LDNOOBW",
        "language": "de",
        "severity": "mixed",
        "tags": [
          "external-import",
          "profanity"
        ],
        "sourceUrl": "https://raw.githubusercontent.com/LDNOOBW/List-of-Dirty-Naughty-Obscene-and-Otherwise-Bad-Words/master/de"
      }
    },
    {
      "id": "imported-ldnoobw-de/möpse",
      "term": "möpse",
      "category": "profanity",
      "scopes": [
        "username",
        "tenantSlug",
        "tenantName"
      ],
      "match": "token",
      "normalizationField": "confusableSkeleton",
      "metadata": {
        "source": "LDNOOBW",
        "language": "de",
        "severity": "mixed",
        "tags": [
          "external-import",
          "profanity"
        ],
        "sourceUrl": "https://raw.githubusercontent.com/LDNOOBW/List-of-Dirty-Naughty-Obscene-and-Otherwise-Bad-Words/master/de"
      }
    },
    {
      "id": "imported-ldnoobw-de/morgenlatte",
      "term": "morgenlatte",
      "category": "profanity",
      "scopes": [
        "username",
        "tenantSlug",
        "tenantName"
      ],
      "match": "token",
      "normalizationField": "confusableSkeleton",
      "metadata": {
        "source": "LDNOOBW",
        "language": "de",
        "severity": "mixed",
        "tags": [
          "external-import",
          "profanity"
        ],
        "sourceUrl": "https://raw.githubusercontent.com/LDNOOBW/List-of-Dirty-Naughty-Obscene-and-Otherwise-Bad-Words/master/de"
      }
    },
    {
      "id": "imported-ldnoobw-de/möse",
      "term": "möse",
      "category": "profanity",
      "scopes": [
        "username",
        "tenantSlug",
        "tenantName"
      ],
      "match": "token",
      "normalizationField": "confusableSkeleton",
      "metadata": {
        "source": "LDNOOBW",
        "language": "de",
        "severity": "mixed",
        "tags": [
          "external-import",
          "profanity"
        ],
        "sourceUrl": "https://raw.githubusercontent.com/LDNOOBW/List-of-Dirty-Naughty-Obscene-and-Otherwise-Bad-Words/master/de"
      }
    },
    {
      "id": "imported-ldnoobw-de/mufti",
      "term": "mufti",
      "category": "profanity",
      "scopes": [
        "username",
        "tenantSlug",
        "tenantName"
      ],
      "match": "token",
      "normalizationField": "confusableSkeleton",
      "metadata": {
        "source": "LDNOOBW",
        "language": "de",
        "severity": "mixed",
        "tags": [
          "external-import",
          "profanity"
        ],
        "sourceUrl": "https://raw.githubusercontent.com/LDNOOBW/List-of-Dirty-Naughty-Obscene-and-Otherwise-Bad-Words/master/de"
      }
    },
    {
      "id": "imported-ldnoobw-de/muschi",
      "term": "muschi",
      "category": "profanity",
      "scopes": [
        "username",
        "tenantSlug",
        "tenantName"
      ],
      "match": "token",
      "normalizationField": "confusableSkeleton",
      "metadata": {
        "source": "LDNOOBW",
        "language": "de",
        "severity": "mixed",
        "tags": [
          "external-import",
          "profanity"
        ],
        "sourceUrl": "https://raw.githubusercontent.com/LDNOOBW/List-of-Dirty-Naughty-Obscene-and-Otherwise-Bad-Words/master/de"
      }
    },
    {
      "id": "imported-ldnoobw-de/nackt",
      "term": "nackt",
      "category": "profanity",
      "scopes": [
        "username",
        "tenantSlug",
        "tenantName"
      ],
      "match": "token",
      "normalizationField": "confusableSkeleton",
      "metadata": {
        "source": "LDNOOBW",
        "language": "de",
        "severity": "mixed",
        "tags": [
          "external-import",
          "profanity"
        ],
        "sourceUrl": "https://raw.githubusercontent.com/LDNOOBW/List-of-Dirty-Naughty-Obscene-and-Otherwise-Bad-Words/master/de"
      }
    },
    {
      "id": "imported-ldnoobw-de/neger",
      "term": "neger",
      "category": "profanity",
      "scopes": [
        "username",
        "tenantSlug",
        "tenantName"
      ],
      "match": "token",
      "normalizationField": "confusableSkeleton",
      "metadata": {
        "source": "LDNOOBW",
        "language": "de",
        "severity": "mixed",
        "tags": [
          "external-import",
          "profanity"
        ],
        "sourceUrl": "https://raw.githubusercontent.com/LDNOOBW/List-of-Dirty-Naughty-Obscene-and-Otherwise-Bad-Words/master/de"
      }
    },
    {
      "id": "imported-ldnoobw-de/nigger",
      "term": "nigger",
      "category": "profanity",
      "scopes": [
        "username",
        "tenantSlug",
        "tenantName"
      ],
      "match": "token",
      "normalizationField": "confusableSkeleton",
      "metadata": {
        "source": "LDNOOBW",
        "language": "de",
        "severity": "mixed",
        "tags": [
          "external-import",
          "profanity"
        ],
        "sourceUrl": "https://raw.githubusercontent.com/LDNOOBW/List-of-Dirty-Naughty-Obscene-and-Otherwise-Bad-Words/master/de"
      }
    },
    {
      "id": "imported-ldnoobw-de/nippel",
      "term": "nippel",
      "category": "profanity",
      "scopes": [
        "username",
        "tenantSlug",
        "tenantName"
      ],
      "match": "token",
      "normalizationField": "confusableSkeleton",
      "metadata": {
        "source": "LDNOOBW",
        "language": "de",
        "severity": "mixed",
        "tags": [
          "external-import",
          "profanity"
        ],
        "sourceUrl": "https://raw.githubusercontent.com/LDNOOBW/List-of-Dirty-Naughty-Obscene-and-Otherwise-Bad-Words/master/de"
      }
    },
    {
      "id": "imported-ldnoobw-de/nutte",
      "term": "nutte",
      "category": "profanity",
      "scopes": [
        "username",
        "tenantSlug",
        "tenantName"
      ],
      "match": "token",
      "normalizationField": "confusableSkeleton",
      "metadata": {
        "source": "LDNOOBW",
        "language": "de",
        "severity": "mixed",
        "tags": [
          "external-import",
          "profanity"
        ],
        "sourceUrl": "https://raw.githubusercontent.com/LDNOOBW/List-of-Dirty-Naughty-Obscene-and-Otherwise-Bad-Words/master/de"
      }
    },
    {
      "id": "imported-ldnoobw-de/onanieren",
      "term": "onanieren",
      "category": "profanity",
      "scopes": [
        "username",
        "tenantSlug",
        "tenantName"
      ],
      "match": "token",
      "normalizationField": "confusableSkeleton",
      "metadata": {
        "source": "LDNOOBW",
        "language": "de",
        "severity": "mixed",
        "tags": [
          "external-import",
          "profanity"
        ],
        "sourceUrl": "https://raw.githubusercontent.com/LDNOOBW/List-of-Dirty-Naughty-Obscene-and-Otherwise-Bad-Words/master/de"
      }
    },
    {
      "id": "imported-ldnoobw-de/orgasmus",
      "term": "orgasmus",
      "category": "profanity",
      "scopes": [
        "username",
        "tenantSlug",
        "tenantName"
      ],
      "match": "token",
      "normalizationField": "confusableSkeleton",
      "metadata": {
        "source": "LDNOOBW",
        "language": "de",
        "severity": "mixed",
        "tags": [
          "external-import",
          "profanity"
        ],
        "sourceUrl": "https://raw.githubusercontent.com/LDNOOBW/List-of-Dirty-Naughty-Obscene-and-Otherwise-Bad-Words/master/de"
      }
    },
    {
      "id": "imported-ldnoobw-de/penis",
      "term": "penis",
      "category": "profanity",
      "scopes": [
        "username",
        "tenantSlug",
        "tenantName"
      ],
      "match": "token",
      "normalizationField": "confusableSkeleton",
      "metadata": {
        "source": "LDNOOBW",
        "language": "de",
        "severity": "mixed",
        "tags": [
          "external-import",
          "profanity"
        ],
        "sourceUrl": "https://raw.githubusercontent.com/LDNOOBW/List-of-Dirty-Naughty-Obscene-and-Otherwise-Bad-Words/master/de"
      }
    },
    {
      "id": "imported-ldnoobw-de/pimmel",
      "term": "pimmel",
      "category": "profanity",
      "scopes": [
        "username",
        "tenantSlug",
        "tenantName"
      ],
      "match": "token",
      "normalizationField": "confusableSkeleton",
      "metadata": {
        "source": "LDNOOBW",
        "language": "de",
        "severity": "mixed",
        "tags": [
          "external-import",
          "profanity"
        ],
        "sourceUrl": "https://raw.githubusercontent.com/LDNOOBW/List-of-Dirty-Naughty-Obscene-and-Otherwise-Bad-Words/master/de"
      }
    },
    {
      "id": "imported-ldnoobw-de/pimpern",
      "term": "pimpern",
      "category": "profanity",
      "scopes": [
        "username",
        "tenantSlug",
        "tenantName"
      ],
      "match": "token",
      "normalizationField": "confusableSkeleton",
      "metadata": {
        "source": "LDNOOBW",
        "language": "de",
        "severity": "mixed",
        "tags": [
          "external-import",
          "profanity"
        ],
        "sourceUrl": "https://raw.githubusercontent.com/LDNOOBW/List-of-Dirty-Naughty-Obscene-and-Otherwise-Bad-Words/master/de"
      }
    },
    {
      "id": "imported-ldnoobw-de/pinkeln",
      "term": "pinkeln",
      "category": "profanity",
      "scopes": [
        "username",
        "tenantSlug",
        "tenantName"
      ],
      "match": "token",
      "normalizationField": "confusableSkeleton",
      "metadata": {
        "source": "LDNOOBW",
        "language": "de",
        "severity": "mixed",
        "tags": [
          "external-import",
          "profanity"
        ],
        "sourceUrl": "https://raw.githubusercontent.com/LDNOOBW/List-of-Dirty-Naughty-Obscene-and-Otherwise-Bad-Words/master/de"
      }
    },
    {
      "id": "imported-ldnoobw-de/pissen",
      "term": "pissen",
      "category": "profanity",
      "scopes": [
        "username",
        "tenantSlug",
        "tenantName"
      ],
      "match": "token",
      "normalizationField": "confusableSkeleton",
      "metadata": {
        "source": "LDNOOBW",
        "language": "de",
        "severity": "mixed",
        "tags": [
          "external-import",
          "profanity"
        ],
        "sourceUrl": "https://raw.githubusercontent.com/LDNOOBW/List-of-Dirty-Naughty-Obscene-and-Otherwise-Bad-Words/master/de"
      }
    },
    {
      "id": "imported-ldnoobw-de/pisser",
      "term": "pisser",
      "category": "profanity",
      "scopes": [
        "username",
        "tenantSlug",
        "tenantName"
      ],
      "match": "token",
      "normalizationField": "confusableSkeleton",
      "metadata": {
        "source": "LDNOOBW",
        "language": "de",
        "severity": "mixed",
        "tags": [
          "external-import",
          "profanity"
        ],
        "sourceUrl": "https://raw.githubusercontent.com/LDNOOBW/List-of-Dirty-Naughty-Obscene-and-Otherwise-Bad-Words/master/de"
      }
    },
    {
      "id": "imported-ldnoobw-de/popel",
      "term": "popel",
      "category": "profanity",
      "scopes": [
        "username",
        "tenantSlug",
        "tenantName"
      ],
      "match": "token",
      "normalizationField": "confusableSkeleton",
      "metadata": {
        "source": "LDNOOBW",
        "language": "de",
        "severity": "mixed",
        "tags": [
          "external-import",
          "profanity"
        ],
        "sourceUrl": "https://raw.githubusercontent.com/LDNOOBW/List-of-Dirty-Naughty-Obscene-and-Otherwise-Bad-Words/master/de"
      }
    },
    {
      "id": "imported-ldnoobw-de/poppen",
      "term": "poppen",
      "category": "profanity",
      "scopes": [
        "username",
        "tenantSlug",
        "tenantName"
      ],
      "match": "token",
      "normalizationField": "confusableSkeleton",
      "metadata": {
        "source": "LDNOOBW",
        "language": "de",
        "severity": "mixed",
        "tags": [
          "external-import",
          "profanity"
        ],
        "sourceUrl": "https://raw.githubusercontent.com/LDNOOBW/List-of-Dirty-Naughty-Obscene-and-Otherwise-Bad-Words/master/de"
      }
    },
    {
      "id": "imported-ldnoobw-de/porno",
      "term": "porno",
      "category": "profanity",
      "scopes": [
        "username",
        "tenantSlug",
        "tenantName"
      ],
      "match": "token",
      "normalizationField": "confusableSkeleton",
      "metadata": {
        "source": "LDNOOBW",
        "language": "de",
        "severity": "mixed",
        "tags": [
          "external-import",
          "profanity"
        ],
        "sourceUrl": "https://raw.githubusercontent.com/LDNOOBW/List-of-Dirty-Naughty-Obscene-and-Otherwise-Bad-Words/master/de"
      }
    },
    {
      "id": "imported-ldnoobw-de/reudig",
      "term": "reudig",
      "category": "profanity",
      "scopes": [
        "username",
        "tenantSlug",
        "tenantName"
      ],
      "match": "token",
      "normalizationField": "confusableSkeleton",
      "metadata": {
        "source": "LDNOOBW",
        "language": "de",
        "severity": "mixed",
        "tags": [
          "external-import",
          "profanity"
        ],
        "sourceUrl": "https://raw.githubusercontent.com/LDNOOBW/List-of-Dirty-Naughty-Obscene-and-Otherwise-Bad-Words/master/de"
      }
    },
    {
      "id": "imported-ldnoobw-de/rosette",
      "term": "rosette",
      "category": "profanity",
      "scopes": [
        "username",
        "tenantSlug",
        "tenantName"
      ],
      "match": "token",
      "normalizationField": "confusableSkeleton",
      "metadata": {
        "source": "LDNOOBW",
        "language": "de",
        "severity": "mixed",
        "tags": [
          "external-import",
          "profanity"
        ],
        "sourceUrl": "https://raw.githubusercontent.com/LDNOOBW/List-of-Dirty-Naughty-Obscene-and-Otherwise-Bad-Words/master/de"
      }
    },
    {
      "id": "imported-ldnoobw-de/schabracke",
      "term": "schabracke",
      "category": "profanity",
      "scopes": [
        "username",
        "tenantSlug",
        "tenantName"
      ],
      "match": "token",
      "normalizationField": "confusableSkeleton",
      "metadata": {
        "source": "LDNOOBW",
        "language": "de",
        "severity": "mixed",
        "tags": [
          "external-import",
          "profanity"
        ],
        "sourceUrl": "https://raw.githubusercontent.com/LDNOOBW/List-of-Dirty-Naughty-Obscene-and-Otherwise-Bad-Words/master/de"
      }
    },
    {
      "id": "imported-ldnoobw-de/scheiße",
      "term": "scheiße",
      "category": "profanity",
      "scopes": [
        "username",
        "tenantSlug",
        "tenantName"
      ],
      "match": "token",
      "normalizationField": "confusableSkeleton",
      "metadata": {
        "source": "LDNOOBW",
        "language": "de",
        "severity": "mixed",
        "tags": [
          "external-import",
          "profanity"
        ],
        "sourceUrl": "https://raw.githubusercontent.com/LDNOOBW/List-of-Dirty-Naughty-Obscene-and-Otherwise-Bad-Words/master/de"
      }
    },
    {
      "id": "imported-ldnoobw-de/scheisser",
      "term": "scheisser",
      "category": "profanity",
      "scopes": [
        "username",
        "tenantSlug",
        "tenantName"
      ],
      "match": "token",
      "normalizationField": "confusableSkeleton",
      "metadata": {
        "source": "LDNOOBW",
        "language": "de",
        "severity": "mixed",
        "tags": [
          "external-import",
          "profanity"
        ],
        "sourceUrl": "https://raw.githubusercontent.com/LDNOOBW/List-of-Dirty-Naughty-Obscene-and-Otherwise-Bad-Words/master/de"
      }
    },
    {
      "id": "imported-ldnoobw-de/schiesser",
      "term": "schiesser",
      "category": "profanity",
      "scopes": [
        "username",
        "tenantSlug",
        "tenantName"
      ],
      "match": "token",
      "normalizationField": "confusableSkeleton",
      "metadata": {
        "source": "LDNOOBW",
        "language": "de",
        "severity": "mixed",
        "tags": [
          "external-import",
          "profanity"
        ],
        "sourceUrl": "https://raw.githubusercontent.com/LDNOOBW/List-of-Dirty-Naughty-Obscene-and-Otherwise-Bad-Words/master/de"
      }
    },
    {
      "id": "imported-ldnoobw-de/schlampe",
      "term": "schlampe",
      "category": "profanity",
      "scopes": [
        "username",
        "tenantSlug",
        "tenantName"
      ],
      "match": "token",
      "normalizationField": "confusableSkeleton",
      "metadata": {
        "source": "LDNOOBW",
        "language": "de",
        "severity": "mixed",
        "tags": [
          "external-import",
          "profanity"
        ],
        "sourceUrl": "https://raw.githubusercontent.com/LDNOOBW/List-of-Dirty-Naughty-Obscene-and-Otherwise-Bad-Words/master/de"
      }
    },
    {
      "id": "imported-ldnoobw-de/schnackeln",
      "term": "schnackeln",
      "category": "profanity",
      "scopes": [
        "username",
        "tenantSlug",
        "tenantName"
      ],
      "match": "token",
      "normalizationField": "confusableSkeleton",
      "metadata": {
        "source": "LDNOOBW",
        "language": "de",
        "severity": "mixed",
        "tags": [
          "external-import",
          "profanity"
        ],
        "sourceUrl": "https://raw.githubusercontent.com/LDNOOBW/List-of-Dirty-Naughty-Obscene-and-Otherwise-Bad-Words/master/de"
      }
    },
    {
      "id": "imported-ldnoobw-de/schwanzlutscher",
      "term": "schwanzlutscher",
      "category": "profanity",
      "scopes": [
        "username",
        "tenantSlug",
        "tenantName"
      ],
      "match": "token",
      "normalizationField": "confusableSkeleton",
      "metadata": {
        "source": "LDNOOBW",
        "language": "de",
        "severity": "mixed",
        "tags": [
          "external-import",
          "profanity"
        ],
        "sourceUrl": "https://raw.githubusercontent.com/LDNOOBW/List-of-Dirty-Naughty-Obscene-and-Otherwise-Bad-Words/master/de"
      }
    },
    {
      "id": "imported-ldnoobw-de/schwuchtel",
      "term": "schwuchtel",
      "category": "profanity",
      "scopes": [
        "username",
        "tenantSlug",
        "tenantName"
      ],
      "match": "token",
      "normalizationField": "confusableSkeleton",
      "metadata": {
        "source": "LDNOOBW",
        "language": "de",
        "severity": "mixed",
        "tags": [
          "external-import",
          "profanity"
        ],
        "sourceUrl": "https://raw.githubusercontent.com/LDNOOBW/List-of-Dirty-Naughty-Obscene-and-Otherwise-Bad-Words/master/de"
      }
    },
    {
      "id": "imported-ldnoobw-de/tittchen",
      "term": "tittchen",
      "category": "profanity",
      "scopes": [
        "username",
        "tenantSlug",
        "tenantName"
      ],
      "match": "token",
      "normalizationField": "confusableSkeleton",
      "metadata": {
        "source": "LDNOOBW",
        "language": "de",
        "severity": "mixed",
        "tags": [
          "external-import",
          "profanity"
        ],
        "sourceUrl": "https://raw.githubusercontent.com/LDNOOBW/List-of-Dirty-Naughty-Obscene-and-Otherwise-Bad-Words/master/de"
      }
    },
    {
      "id": "imported-ldnoobw-de/titten",
      "term": "titten",
      "category": "profanity",
      "scopes": [
        "username",
        "tenantSlug",
        "tenantName"
      ],
      "match": "token",
      "normalizationField": "confusableSkeleton",
      "metadata": {
        "source": "LDNOOBW",
        "language": "de",
        "severity": "mixed",
        "tags": [
          "external-import",
          "profanity"
        ],
        "sourceUrl": "https://raw.githubusercontent.com/LDNOOBW/List-of-Dirty-Naughty-Obscene-and-Otherwise-Bad-Words/master/de"
      }
    },
    {
      "id": "imported-ldnoobw-de/vögeln",
      "term": "vögeln",
      "category": "profanity",
      "scopes": [
        "username",
        "tenantSlug",
        "tenantName"
      ],
      "match": "token",
      "normalizationField": "confusableSkeleton",
      "metadata": {
        "source": "LDNOOBW",
        "language": "de",
        "severity": "mixed",
        "tags": [
          "external-import",
          "profanity"
        ],
        "sourceUrl": "https://raw.githubusercontent.com/LDNOOBW/List-of-Dirty-Naughty-Obscene-and-Otherwise-Bad-Words/master/de"
      }
    },
    {
      "id": "imported-ldnoobw-de/vollpfosten",
      "term": "vollpfosten",
      "category": "profanity",
      "scopes": [
        "username",
        "tenantSlug",
        "tenantName"
      ],
      "match": "token",
      "normalizationField": "confusableSkeleton",
      "metadata": {
        "source": "LDNOOBW",
        "language": "de",
        "severity": "mixed",
        "tags": [
          "external-import",
          "profanity"
        ],
        "sourceUrl": "https://raw.githubusercontent.com/LDNOOBW/List-of-Dirty-Naughty-Obscene-and-Otherwise-Bad-Words/master/de"
      }
    },
    {
      "id": "imported-ldnoobw-de/wichse",
      "term": "wichse",
      "category": "profanity",
      "scopes": [
        "username",
        "tenantSlug",
        "tenantName"
      ],
      "match": "token",
      "normalizationField": "confusableSkeleton",
      "metadata": {
        "source": "LDNOOBW",
        "language": "de",
        "severity": "mixed",
        "tags": [
          "external-import",
          "profanity"
        ],
        "sourceUrl": "https://raw.githubusercontent.com/LDNOOBW/List-of-Dirty-Naughty-Obscene-and-Otherwise-Bad-Words/master/de"
      }
    },
    {
      "id": "imported-ldnoobw-de/wichsen",
      "term": "wichsen",
      "category": "profanity",
      "scopes": [
        "username",
        "tenantSlug",
        "tenantName"
      ],
      "match": "token",
      "normalizationField": "confusableSkeleton",
      "metadata": {
        "source": "LDNOOBW",
        "language": "de",
        "severity": "mixed",
        "tags": [
          "external-import",
          "profanity"
        ],
        "sourceUrl": "https://raw.githubusercontent.com/LDNOOBW/List-of-Dirty-Naughty-Obscene-and-Otherwise-Bad-Words/master/de"
      }
    },
    {
      "id": "imported-ldnoobw-de/wichser",
      "term": "wichser",
      "category": "profanity",
      "scopes": [
        "username",
        "tenantSlug",
        "tenantName"
      ],
      "match": "token",
      "normalizationField": "confusableSkeleton",
      "metadata": {
        "source": "LDNOOBW",
        "language": "de",
        "severity": "mixed",
        "tags": [
          "external-import",
          "profanity"
        ],
        "sourceUrl": "https://raw.githubusercontent.com/LDNOOBW/List-of-Dirty-Naughty-Obscene-and-Otherwise-Bad-Words/master/de"
      }
    }
  ]
}
