{
  "id": "imported-ldnoobw-eo",
  "description": "Imported LDNOOBW snapshot (eo)",
  "metadata": {
    "source": "LDNOOBW",
    "language": "eo",
    "severity": "mixed",
    "tags": [
      "external-import",
      "profanity"
    ],
    "sourceUrl": "https://raw.githubusercontent.com/LDNOOBW/List-of-Dirty-Naughty-Obscene-and-Otherwise-Bad-Words/master/eo"
  },
  "rules": [
    {
      "id": "imported-ldnoobw-eo/bugren",
      "term": "bugren",
      "category": "profanity",
      "scopes": [
        "username",
        "tenantSlug",
        "tenantName"
      ],
      "match": "token",
      "normalizationField": "confusableSkeleton",
      "metadata": {
        "source": "LDNOOBW",
        "language": "eo",
        "severity": "mixed",
        "tags": [
          "external-import",
          "profanity"
        ],
        "sourceUrl": "https://raw.githubusercontent.com/LDNOOBW/List-of-Dirty-Naughty-Obscene-and-Otherwise-Bad-Words/master/eo"
      }
    },
    {
      "id": "imported-ldnoobw-eo/bugri",
      "term": "bugri",
      "category": "profanity",
      "scopes": [
        "username",
        "tenantSlug",
        "tenantName"
      ],
      "match": "token",
      "normalizationField": "confusableSkeleton",
      "metadata": {
        "source": "LDNOOBW",
        "language": "eo",
        "severity": "mixed",
        "tags": [
          "external-import",
          "profanity"
        ],
        "sourceUrl": "https://raw.githubusercontent.com/LDNOOBW/List-of-Dirty-Naughty-Obscene-and-Otherwise-Bad-Words/master/eo"
      }
    },
    {
      "id": "imported-ldnoobw-eo/bugru",
      "term": "bugru",
      "category": "profanity",
      "scopes": [
        "username",
        "tenantSlug",
        "tenantName"
      ],
      "match": "token",
      "normalizationField": "confusableSkeleton",
      "metadata": {
        "source": "LDNOOBW",
        "language": "eo",
        "severity": "mixed",
        "tags": [
          "external-import",
          "profanity"
        ],
        "sourceUrl": "https://raw.githubusercontent.com/LDNOOBW/List-of-Dirty-Naughty-Obscene-and-Otherwise-Bad-Words/master/eo"
      }
    },
    {
      "id": "imported-ldnoobw-eo/ĉiesulino",
      "term": "ĉiesulino",
      "category": "profanity",
      "scopes": [
        "username",
        "tenantSlug",
        "tenantName"
      ],
      "match": "token",
      "normalizationField": "confusableSkeleton",
      "metadata": {
        "source": "LDNOOBW",
        "language": "eo",
        "severity": "mixed",
        "tags": [
          "external-import",
          "profanity"
        ],
        "sourceUrl": "https://raw.githubusercontent.com/LDNOOBW/List-of-Dirty-Naughty-Obscene-and-Otherwise-Bad-Words/master/eo"
      }
    },
    {
      "id": "imported-ldnoobw-eo/ĉiesulo",
      "term": "ĉiesulo",
      "category": "profanity",
      "scopes": [
        "username",
        "tenantSlug",
        "tenantName"
      ],
      "match": "token",
      "normalizationField": "confusableSkeleton",
      "metadata": {
        "source": "LDNOOBW",
        "language": "eo",
        "severity": "mixed",
        "tags": [
          "external-import",
          "profanity"
        ],
        "sourceUrl": "https://raw.githubusercontent.com/LDNOOBW/List-of-Dirty-Naughty-Obscene-and-Otherwise-Bad-Words/master/eo"
      }
    },
    {
      "id": "imported-ldnoobw-eo/diofek",
      "term": "diofek",
      "category": "profanity",
      "scopes": [
        "username",
        "tenantSlug",
        "tenantName"
      ],
      "match": "token",
      "normalizationField": "confusableSkeleton",
      "metadata": {
        "source": "LDNOOBW",
        "language": "eo",
        "severity": "mixed",
        "tags": [
          "external-import",
          "profanity"
        ],
        "sourceUrl": "https://raw.githubusercontent.com/LDNOOBW/List-of-Dirty-Naughty-Obscene-and-Otherwise-Bad-Words/master/eo"
      }
    },
    {
      "id": "imported-ldnoobw-eo/diofeka",
      "term": "diofeka",
      "category": "profanity",
      "scopes": [
        "username",
        "tenantSlug",
        "tenantName"
      ],
      "match": "token",
      "normalizationField": "confusableSkeleton",
      "metadata": {
        "source": "LDNOOBW",
        "language": "eo",
        "severity": "mixed",
        "tags": [
          "external-import",
          "profanity"
        ],
        "sourceUrl": "https://raw.githubusercontent.com/LDNOOBW/List-of-Dirty-Naughty-Obscene-and-Otherwise-Bad-Words/master/eo"
      }
    },
    {
      "id": "imported-ldnoobw-eo/fek",
      "term": "fek",
      "category": "profanity",
      "scopes": [
        "username",
        "tenantSlug",
        "tenantName"
      ],
      "match": "token",
      "normalizationField": "confusableSkeleton",
      "metadata": {
        "source": "LDNOOBW",
        "language": "eo",
        "severity": "mixed",
        "tags": [
          "external-import",
          "profanity"
        ],
        "sourceUrl": "https://raw.githubusercontent.com/LDNOOBW/List-of-Dirty-Naughty-Obscene-and-Otherwise-Bad-Words/master/eo"
      }
    },
    {
      "id": "imported-ldnoobw-eo/feken",
      "term": "feken",
      "category": "profanity",
      "scopes": [
        "username",
        "tenantSlug",
        "tenantName"
      ],
      "match": "token",
      "normalizationField": "confusableSkeleton",
      "metadata": {
        "source": "LDNOOBW",
        "language": "eo",
        "severity": "mixed",
        "tags": [
          "external-import",
          "profanity"
        ],
        "sourceUrl": "https://raw.githubusercontent.com/LDNOOBW/List-of-Dirty-Naughty-Obscene-and-Otherwise-Bad-Words/master/eo"
      }
    },
    {
      "id": "imported-ldnoobw-eo/fekfikanto",
      "term": "fekfikanto",
      "category": "profanity",
      "scopes": [
        "username",
        "tenantSlug",
        "tenantName"
      ],
      "match": "token",
      "normalizationField": "confusableSkeleton",
      "metadata": {
        "source": "LDNOOBW",
        "language": "eo",
        "severity": "mixed",
        "tags": [
          "external-import",
          "profanity"
        ],
        "sourceUrl": "https://raw.githubusercontent.com/LDNOOBW/List-of-Dirty-Naughty-Obscene-and-Otherwise-Bad-Words/master/eo"
      }
    },
    {
      "id": "imported-ldnoobw-eo/feklekulo",
      "term": "feklekulo",
      "category": "profanity",
      "scopes": [
        "username",
        "tenantSlug",
        "tenantName"
      ],
      "match": "token",
      "normalizationField": "confusableSkeleton",
      "metadata": {
        "source": "LDNOOBW",
        "language": "eo",
        "severity": "mixed",
        "tags": [
          "external-import",
          "profanity"
        ],
        "sourceUrl": "https://raw.githubusercontent.com/LDNOOBW/List-of-Dirty-Naughty-Obscene-and-Otherwise-Bad-Words/master/eo"
      }
    },
    {
      "id": "imported-ldnoobw-eo/fekulo",
      "term": "fekulo",
      "category": "profanity",
      "scopes": [
        "username",
        "tenantSlug",
        "tenantName"
      ],
      "match": "token",
      "normalizationField": "confusableSkeleton",
      "metadata": {
        "source": "LDNOOBW",
        "language": "eo",
        "severity": "mixed",
        "tags": [
          "external-import",
          "profanity"
        ],
        "sourceUrl": "https://raw.githubusercontent.com/LDNOOBW/List-of-Dirty-Naughty-Obscene-and-Otherwise-Bad-Words/master/eo"
      }
    },
    {
      "id": "imported-ldnoobw-eo/fik",
      "term": "fik",
      "category": "profanity",
      "scopes": [
        "username",
        "tenantSlug",
        "tenantName"
      ],
      "match": "token",
      "normalizationField": "confusableSkeleton",
      "metadata": {
        "source": "LDNOOBW",
        "language": "eo",
        "severity": "mixed",
        "tags": [
          "external-import",
          "profanity"
        ],
        "sourceUrl": "https://raw.githubusercontent.com/LDNOOBW/List-of-Dirty-Naughty-Obscene-and-Otherwise-Bad-Words/master/eo"
      }
    },
    {
      "id": "imported-ldnoobw-eo/fikado",
      "term": "fikado",
      "category": "profanity",
      "scopes": [
        "username",
        "tenantSlug",
        "tenantName"
      ],
      "match": "token",
      "normalizationField": "confusableSkeleton",
      "metadata": {
        "source": "LDNOOBW",
        "language": "eo",
        "severity": "mixed",
        "tags": [
          "external-import",
          "profanity"
        ],
        "sourceUrl": "https://raw.githubusercontent.com/LDNOOBW/List-of-Dirty-Naughty-Obscene-and-Otherwise-Bad-Words/master/eo"
      }
    },
    {
      "id": "imported-ldnoobw-eo/fikema",
      "term": "fikema",
      "category": "profanity",
      "scopes": [
        "username",
        "tenantSlug",
        "tenantName"
      ],
      "match": "token",
      "normalizationField": "confusableSkeleton",
      "metadata": {
        "source": "LDNOOBW",
        "language": "eo",
        "severity": "mixed",
        "tags": [
          "external-import",
          "profanity"
        ],
        "sourceUrl": "https://raw.githubusercontent.com/LDNOOBW/List-of-Dirty-Naughty-Obscene-and-Otherwise-Bad-Words/master/eo"
      }
    },
    {
      "id": "imported-ldnoobw-eo/fikfek",
      "term": "fikfek",
      "category": "profanity",
      "scopes": [
        "username",
        "tenantSlug",
        "tenantName"
      ],
      "match": "token",
      "normalizationField": "confusableSkeleton",
      "metadata": {
        "source": "LDNOOBW",
        "language": "eo",
        "severity": "mixed",
        "tags": [
          "external-import",
          "profanity"
        ],
        "sourceUrl": "https://raw.githubusercontent.com/LDNOOBW/List-of-Dirty-Naughty-Obscene-and-Otherwise-Bad-Words/master/eo"
      }
    },
    {
      "id": "imported-ldnoobw-eo/fiki",
      "term": "fiki",
      "category": "profanity",
      "scopes": [
        "username",
        "tenantSlug",
        "tenantName"
      ],
      "match": "token",
      "normalizationField": "confusableSkeleton",
      "metadata": {
        "source": "LDNOOBW",
        "language": "eo",
        "severity": "mixed",
        "tags": [
          "external-import",
          "profanity"
        ],
        "sourceUrl": "https://raw.githubusercontent.com/LDNOOBW/List-of-Dirty-Naughty-Obscene-and-Otherwise-Bad-Words/master/eo"
      }
    },
    {
      "id": "imported-ldnoobw-eo/fikiĝi",
      "term": "fikiĝi",
      "category": "profanity",
      "scopes": [
        "username",
        "tenantSlug",
        "tenantName"
      ],
      "match": "token",
      "normalizationField": "confusableSkeleton",
      "metadata": {
        "source": "LDNOOBW",
        "language": "eo",
        "severity": "mixed",
        "tags": [
          "external-import",
          "profanity"
        ],
        "sourceUrl": "https://raw.githubusercontent.com/LDNOOBW/List-of-Dirty-Naughty-Obscene-and-Otherwise-Bad-Words/master/eo"
      }
    },
    {
      "id": "imported-ldnoobw-eo/fikiĝu",
      "term": "fikiĝu",
      "category": "profanity",
      "scopes": [
        "username",
        "tenantSlug",
        "tenantName"
      ],
      "match": "token",
      "normalizationField": "confusableSkeleton",
      "metadata": {
        "source": "LDNOOBW",
        "language": "eo",
        "severity": "mixed",
        "tags": [
          "external-import",
          "profanity"
        ],
        "sourceUrl": "https://raw.githubusercontent.com/LDNOOBW/List-of-Dirty-Naughty-Obscene-and-Otherwise-Bad-Words/master/eo"
      }
    },
    {
      "id": "imported-ldnoobw-eo/fikilo",
      "term": "fikilo",
      "category": "profanity",
      "scopes": [
        "username",
        "tenantSlug",
        "tenantName"
      ],
      "match": "token",
      "normalizationField": "confusableSkeleton",
      "metadata": {
        "source": "LDNOOBW",
        "language": "eo",
        "severity": "mixed",
        "tags": [
          "external-import",
          "profanity"
        ],
        "sourceUrl": "https://raw.githubusercontent.com/LDNOOBW/List-of-Dirty-Naughty-Obscene-and-Otherwise-Bad-Words/master/eo"
      }
    },
    {
      "id": "imported-ldnoobw-eo/fikklaŭno",
      "term": "fikklaŭno",
      "category": "profanity",
      "scopes": [
        "username",
        "tenantSlug",
        "tenantName"
      ],
      "match": "token",
      "normalizationField": "confusableSkeleton",
      "metadata": {
        "source": "LDNOOBW",
        "language": "eo",
        "severity": "mixed",
        "tags": [
          "external-import",
          "profanity"
        ],
        "sourceUrl": "https://raw.githubusercontent.com/LDNOOBW/List-of-Dirty-Naughty-Obscene-and-Otherwise-Bad-Words/master/eo"
      }
    },
    {
      "id": "imported-ldnoobw-eo/fikota",
      "term": "fikota",
      "category": "profanity",
      "scopes": [
        "username",
        "tenantSlug",
        "tenantName"
      ],
      "match": "token",
      "normalizationField": "confusableSkeleton",
      "metadata": {
        "source": "LDNOOBW",
        "language": "eo",
        "severity": "mixed",
        "tags": [
          "external-import",
          "profanity"
        ],
        "sourceUrl": "https://raw.githubusercontent.com/LDNOOBW/List-of-Dirty-Naughty-Obscene-and-Otherwise-Bad-Words/master/eo"
      }
    },
    {
      "id": "imported-ldnoobw-eo/fiku",
      "term": "fiku",
      "category": "profanity",
      "scopes": [
        "username",
        "tenantSlug",
        "tenantName"
      ],
      "match": "token",
      "normalizationField": "confusableSkeleton",
      "metadata": {
        "source": "LDNOOBW",
        "language": "eo",
        "severity": "mixed",
        "tags": [
          "external-import",
          "profanity"
        ],
        "sourceUrl": "https://raw.githubusercontent.com/LDNOOBW/List-of-Dirty-Naughty-Obscene-and-Otherwise-Bad-Words/master/eo"
      }
    },
    {
      "id": "imported-ldnoobw-eo/forfiki",
      "term": "forfiki",
      "category": "profanity",
      "scopes": [
        "username",
        "tenantSlug",
        "tenantName"
      ],
      "match": "token",
      "normalizationField": "confusableSkeleton",
      "metadata": {
        "source": "LDNOOBW",
        "language": "eo",
        "severity": "mixed",
        "tags": [
          "external-import",
          "profanity"
        ],
        "sourceUrl": "https://raw.githubusercontent.com/LDNOOBW/List-of-Dirty-Naughty-Obscene-and-Otherwise-Bad-Words/master/eo"
      }
    },
    {
      "id": "imported-ldnoobw-eo/forfikiĝu",
      "term": "forfikiĝu",
      "category": "profanity",
      "scopes": [
        "username",
        "tenantSlug",
        "tenantName"
      ],
      "match": "token",
      "normalizationField": "confusableSkeleton",
      "metadata": {
        "source": "LDNOOBW",
        "language": "eo",
        "severity": "mixed",
        "tags": [
          "external-import",
          "profanity"
        ],
        "sourceUrl": "https://raw.githubusercontent.com/LDNOOBW/List-of-Dirty-Naughty-Obscene-and-Otherwise-Bad-Words/master/eo"
      }
    },
    {
      "id": "imported-ldnoobw-eo/forfiku",
      "term": "forfiku",
      "category": "profanity",
      "scopes": [
        "username",
        "tenantSlug",
        "tenantName"
      ],
      "match": "token",
      "normalizationField": "confusableSkeleton",
      "metadata": {
        "source": "LDNOOBW",
        "language": "eo",
        "severity": "mixed",
        "tags": [
          "external-import",
          "profanity"
        ],
        "sourceUrl": "https://raw.githubusercontent.com/LDNOOBW/List-of-Dirty-Naughty-Obscene-and-Otherwise-Bad-Words/master/eo"
      }
    },
    {
      "id": "imported-ldnoobw-eo/forfurzu",
      "term": "forfurzu",
      "category": "profanity",
      "scopes": [
        "username",
        "tenantSlug",
        "tenantName"
      ],
      "match": "token",
      "normalizationField": "confusableSkeleton",
      "metadata": {
        "source": "LDNOOBW",
        "language": "eo",
        "severity": "mixed",
        "tags": [
          "external-import",
          "profanity"
        ],
        "sourceUrl": "https://raw.githubusercontent.com/LDNOOBW/List-of-Dirty-Naughty-Obscene-and-Otherwise-Bad-Words/master/eo"
      }
    },
    {
      "id": "imported-ldnoobw-eo/forpisi",
      "term": "forpisi",
      "category": "profanity",
      "scopes": [
        "username",
        "tenantSlug",
        "tenantName"
      ],
      "match": "token",
      "normalizationField": "confusableSkeleton",
      "metadata": {
        "source": "LDNOOBW",
        "language": "eo",
        "severity": "mixed",
        "tags": [
          "external-import",
          "profanity"
        ],
        "sourceUrl": "https://raw.githubusercontent.com/LDNOOBW/List-of-Dirty-Naughty-Obscene-and-Otherwise-Bad-Words/master/eo"
      }
    },
    {
      "id": "imported-ldnoobw-eo/forpisu",
      "term": "forpisu",
      "category": "profanity",
      "scopes": [
        "username",
        "tenantSlug",
        "tenantName"
      ],
      "match": "token",
      "normalizationField": "confusableSkeleton",
      "metadata": {
        "source": "LDNOOBW",
        "language": "eo",
        "severity": "mixed",
        "tags": [
          "external-import",
          "profanity"
        ],
        "sourceUrl": "https://raw.githubusercontent.com/LDNOOBW/List-of-Dirty-Naughty-Obscene-and-Otherwise-Bad-Words/master/eo"
      }
    },
    {
      "id": "imported-ldnoobw-eo/furzulo",
      "term": "furzulo",
      "category": "profanity",
      "scopes": [
        "username",
        "tenantSlug",
        "tenantName"
      ],
      "match": "token",
      "normalizationField": "confusableSkeleton",
      "metadata": {
        "source": "LDNOOBW",
        "language": "eo",
        "severity": "mixed",
        "tags": [
          "external-import",
          "profanity"
        ],
        "sourceUrl": "https://raw.githubusercontent.com/LDNOOBW/List-of-Dirty-Naughty-Obscene-and-Otherwise-Bad-Words/master/eo"
      }
    },
    {
      "id": "imported-ldnoobw-eo/kacen",
      "term": "kacen",
      "category": "profanity",
      "scopes": [
        "username",
        "tenantSlug",
        "tenantName"
      ],
      "match": "token",
      "normalizationField": "confusableSkeleton",
      "metadata": {
        "source": "LDNOOBW",
        "language": "eo",
        "severity": "mixed",
        "tags": [
          "external-import",
          "profanity"
        ],
        "sourceUrl": "https://raw.githubusercontent.com/LDNOOBW/List-of-Dirty-Naughty-Obscene-and-Otherwise-Bad-Words/master/eo"
      }
    },
    {
      "id": "imported-ldnoobw-eo/kaco",
      "term": "kaco",
      "category": "profanity",
      "scopes": [
        "username",
        "tenantSlug",
        "tenantName"
      ],
      "match": "token",
      "normalizationField": "confusableSkeleton",
      "metadata": {
        "source": "LDNOOBW",
        "language": "eo",
        "severity": "mixed",
        "tags": [
          "external-import",
          "profanity"
        ],
        "sourceUrl": "https://raw.githubusercontent.com/LDNOOBW/List-of-Dirty-Naughty-Obscene-and-Otherwise-Bad-Words/master/eo"
      }
    },
    {
      "id": "imported-ldnoobw-eo/kacsuĉulo",
      "term": "kacsuĉulo",
      "category": "profanity",
      "scopes": [
        "username",
        "tenantSlug",
        "tenantName"
      ],
      "match": "token",
      "normalizationField": "confusableSkeleton",
      "metadata": {
        "source": "LDNOOBW",
        "language": "eo",
        "severity": "mixed",
        "tags": [
          "external-import",
          "profanity"
        ],
        "sourceUrl": "https://raw.githubusercontent.com/LDNOOBW/List-of-Dirty-Naughty-Obscene-and-Otherwise-Bad-Words/master/eo"
      }
    },
    {
      "id": "imported-ldnoobw-eo/kojono",
      "term": "kojono",
      "category": "profanity",
      "scopes": [
        "username",
        "tenantSlug",
        "tenantName"
      ],
      "match": "token",
      "normalizationField": "confusableSkeleton",
      "metadata": {
        "source": "LDNOOBW",
        "language": "eo",
        "severity": "mixed",
        "tags": [
          "external-import",
          "profanity"
        ],
        "sourceUrl": "https://raw.githubusercontent.com/LDNOOBW/List-of-Dirty-Naughty-Obscene-and-Otherwise-Bad-Words/master/eo"
      }
    },
    {
      "id": "imported-ldnoobw-eo/piĉen",
      "term": "piĉen",
      "category": "profanity",
      "scopes": [
        "username",
        "tenantSlug",
        "tenantName"
      ],
      "match": "token",
      "normalizationField": "confusableSkeleton",
      "metadata": {
        "source": "LDNOOBW",
        "language": "eo",
        "severity": "mixed",
        "tags": [
          "external-import",
          "profanity"
        ],
        "sourceUrl": "https://raw.githubusercontent.com/LDNOOBW/List-of-Dirty-Naughty-Obscene-and-Otherwise-Bad-Words/master/eo"
      }
    },
    {
      "id": "imported-ldnoobw-eo/piĉo",
      "term": "piĉo",
      "category": "profanity",
      "scopes": [
        "username",
        "tenantSlug",
        "tenantName"
      ],
      "match": "token",
      "normalizationField": "confusableSkeleton",
      "metadata": {
        "source": "LDNOOBW",
        "language": "eo",
        "severity": "mixed",
        "tags": [
          "external-import",
          "profanity"
        ],
        "sourceUrl": "https://raw.githubusercontent.com/LDNOOBW/List-of-Dirty-Naughty-Obscene-and-Otherwise-Bad-Words/master/eo"
      }
    },
    {
      "id": "imported-ldnoobw-eo/zamenfek",
      "term": "zamenfek",
      "category": "profanity",
      "scopes": [
        "username",
        "tenantSlug",
        "tenantName"
      ],
      "match": "token",
      "normalizationField": "confusableSkeleton",
      "metadata": {
        "source": "LDNOOBW",
        "language": "eo",
        "severity": "mixed",
        "tags": [
          "external-import",
          "profanity"
        ],
        "sourceUrl": "https://raw.githubusercontent.com/LDNOOBW/List-of-Dirty-Naughty-Obscene-and-Otherwise-Bad-Words/master/eo"
      }
    }
  ]
}
